[
{ "model":"game.Matchup", "pk":1120401, "fields":{"espn_game_id":240912016, "year":2004, "date":"2004-09-12", "week_number":1, "bye":false, "home_team":12, "away_team":1, "win":true, "home_team_points":35, "away_team_points":17} },
{ "model":"game.Matchup", "pk":2030401, "fields":{"espn_game_id":240912021, "year":2004, "date":"2004-09-12", "week_number":1, "bye":false, "home_team":3, "away_team":2, "win":true, "home_team_points":31, "away_team_points":17} },
{ "model":"game.Matchup", "pk":4160401, "fields":{"espn_game_id":240912028, "year":2004, "date":"2004-09-12", "week_number":1, "bye":false, "home_team":4, "away_team":16, "win":true, "home_team_points":16, "away_team_points":10} },
{ "model":"game.Matchup", "pk":5080401, "fields":{"espn_game_id":240912014, "year":2004, "date":"2004-09-12", "week_number":1, "bye":false, "home_team":8, "away_team":5, "win":true, "home_team_points":17, "away_team_points":10} },
{ "model":"game.Matchup", "pk":6130401, "fields":{"espn_game_id":240912025, "year":2004, "date":"2004-09-12", "week_number":1, "bye":false, "home_team":6, "away_team":13, "win":false, "home_team_points":19, "away_team_points":21} },
{ "model":"game.Matchup", "pk":7150401, "fields":{"espn_game_id":240912018, "year":2004, "date":"2004-09-12", "week_number":1, "bye":false, "home_team":15, "away_team":7, "win":false, "home_team_points":7, "away_team_points":21} },
{ "model":"game.Matchup", "pk":9100401, "fields":{"espn_game_id":240912003, "year":2004, "date":"2004-09-12", "week_number":1, "bye":false, "home_team":9, "away_team":10, "win":false, "home_team_points":16, "away_team_points":20} },
{ "model":"game.Matchup", "pk":11140401, "fields":{"espn_game_id":240913029, "year":2004, "date":"2004-09-13", "week_number":1, "bye":false, "home_team":14, "away_team":11, "win":false, "home_team_points":14, "away_team_points":24} },
{ "model":"game.Matchup", "pk":17310401, "fields":{"espn_game_id":240912002, "year":2004, "date":"2004-09-12", "week_number":1, "bye":false, "home_team":17, "away_team":31, "win":false, "home_team_points":10, "away_team_points":13} },
{ "model":"game.Matchup", "pk":18320401, "fields":{"espn_game_id":240911015, "year":2004, "date":"2004-09-11", "week_number":1, "bye":false, "home_team":18, "away_team":32, "win":false, "home_team_points":7, "away_team_points":17} },
{ "model":"game.Matchup", "pk":19300401, "fields":{"espn_game_id":240909017, "year":2004, "date":"2004-09-09", "week_number":1, "bye":false, "home_team":19, "away_team":30, "win":true, "home_team_points":27, "away_team_points":24} },
{ "model":"game.Matchup", "pk":20260401, "fields":{"espn_game_id":240912020, "year":2004, "date":"2004-09-12", "week_number":1, "bye":false, "home_team":20, "away_team":26, "win":true, "home_team_points":31, "away_team_points":24} },
{ "model":"game.Matchup", "pk":21220401, "fields":{"espn_game_id":240912007, "year":2004, "date":"2004-09-12", "week_number":1, "bye":false, "home_team":21, "away_team":22, "win":true, "home_team_points":34, "away_team_points":24} },
{ "model":"game.Matchup", "pk":23280401, "fields":{"espn_game_id":240912023, "year":2004, "date":"2004-09-12", "week_number":1, "bye":false, "home_team":28, "away_team":23, "win":true, "home_team_points":24, "away_team_points":21} },
{ "model":"game.Matchup", "pk":24290401, "fields":{"espn_game_id":240912034, "year":2004, "date":"2004-09-12", "week_number":1, "bye":false, "home_team":29, "away_team":24, "win":false, "home_team_points":20, "away_team_points":27} },
{ "model":"game.Matchup", "pk":25270401, "fields":{"espn_game_id":240912005, "year":2004, "date":"2004-09-12", "week_number":1, "bye":false, "home_team":27, "away_team":25, "win":true, "home_team_points":20, "away_team_points":3} },
{ "model":"game.Matchup", "pk":1270402, "fields":{"espn_game_id":240919006, "year":2004, "date":"2004-09-19", "week_number":2, "bye":false, "home_team":1, "away_team":27, "win":true, "home_team_points":19, "away_team_points":12} },
{ "model":"game.Matchup", "pk":2040402, "fields":{"espn_game_id":240919019, "year":2004, "date":"2004-09-19", "week_number":2, "bye":false, "home_team":2, "away_team":4, "win":true, "home_team_points":20, "away_team_points":14} },
{ "model":"game.Matchup", "pk":3120402, "fields":{"espn_game_id":240920021, "year":2004, "date":"2004-09-20", "week_number":2, "bye":false, "home_team":3, "away_team":12, "win":true, "home_team_points":27, "away_team_points":16} },
{ "model":"game.Matchup", "pk":5190402, "fields":{"espn_game_id":240919022, "year":2004, "date":"2004-09-19", "week_number":2, "bye":false, "home_team":5, "away_team":19, "win":false, "home_team_points":12, "away_team_points":23} },
{ "model":"game.Matchup", "pk":6150402, "fields":{"espn_game_id":240919018, "year":2004, "date":"2004-09-19", "week_number":2, "bye":false, "home_team":15, "away_team":6, "win":true, "home_team_points":30, "away_team_points":27} },
{ "model":"game.Matchup", "pk":7160402, "fields":{"espn_game_id":240919027, "year":2004, "date":"2004-09-19", "week_number":2, "bye":false, "home_team":16, "away_team":7, "win":false, "home_team_points":6, "away_team_points":10} },
{ "model":"game.Matchup", "pk":8130402, "fields":{"espn_game_id":240919001, "year":2004, "date":"2004-09-19", "week_number":2, "bye":false, "home_team":13, "away_team":8, "win":true, "home_team_points":34, "away_team_points":17} },
{ "model":"game.Matchup", "pk":9110402, "fields":{"espn_game_id":240919009, "year":2004, "date":"2004-09-19", "week_number":2, "bye":false, "home_team":11, "away_team":9, "win":false, "home_team_points":10, "away_team_points":21} },
{ "model":"game.Matchup", "pk":10290402, "fields":{"espn_game_id":240919008, "year":2004, "date":"2004-09-19", "week_number":2, "bye":false, "home_team":10, "away_team":29, "win":true, "home_team_points":28, "away_team_points":16} },
{ "model":"game.Matchup", "pk":14220402, "fields":{"espn_game_id":240919012, "year":2004, "date":"2004-09-19", "week_number":2, "bye":false, "home_team":22, "away_team":14, "win":false, "home_team_points":17, "away_team_points":28} },
{ "model":"game.Matchup", "pk":17230402, "fields":{"espn_game_id":240919013, "year":2004, "date":"2004-09-19", "week_number":2, "bye":false, "home_team":23, "away_team":17, "win":true, "home_team_points":13, "away_team_points":10} },
{ "model":"game.Matchup", "pk":18260402, "fields":{"espn_game_id":240919004, "year":2004, "date":"2004-09-19", "week_number":2, "bye":false, "home_team":26, "away_team":18, "win":true, "home_team_points":16, "away_team_points":13} },
{ "model":"game.Matchup", "pk":20240402, "fields":{"espn_game_id":240919024, "year":2004, "date":"2004-09-19", "week_number":2, "bye":false, "home_team":24, "away_team":20, "win":false, "home_team_points":28, "away_team_points":34} },
{ "model":"game.Matchup", "pk":21310402, "fields":{"espn_game_id":240919030, "year":2004, "date":"2004-09-19", "week_number":2, "bye":false, "home_team":31, "away_team":21, "win":true, "home_team_points":7, "away_team_points":6} },
{ "model":"game.Matchup", "pk":25280402, "fields":{"espn_game_id":240919033, "year":2004, "date":"2004-09-19", "week_number":2, "bye":false, "home_team":25, "away_team":28, "win":true, "home_team_points":30, "away_team_points":13} },
{ "model":"game.Matchup", "pk":30320402, "fields":{"espn_game_id":240919010, "year":2004, "date":"2004-09-19", "week_number":2, "bye":false, "home_team":32, "away_team":30, "win":false, "home_team_points":17, "away_team_points":31} },
{ "model":"game.Matchup", "pk":1040403, "fields":{"espn_game_id":240927028, "year":2004, "date":"2004-09-27", "week_number":3, "bye":false, "home_team":4, "away_team":1, "win":false, "home_team_points":18, "away_team_points":21} },
{ "model":"game.Matchup", "pk":2270403, "fields":{"espn_game_id":240926019, "year":2004, "date":"2004-09-26", "week_number":3, "bye":false, "home_team":2, "away_team":27, "win":true, "home_team_points":27, "away_team_points":10} },
{ "model":"game.Matchup", "pk":3100403, "fields":{"espn_game_id":240926008, "year":2004, "date":"2004-09-26", "week_number":3, "bye":false, "home_team":10, "away_team":3, "win":false, "home_team_points":13, "away_team_points":30} },
{ "model":"game.Matchup", "pk":5130403, "fields":{"espn_game_id":240926001, "year":2004, "date":"2004-09-26", "week_number":3, "bye":false, "home_team":13, "away_team":5, "win":true, "home_team_points":6, "away_team_points":3} },
{ "model":"game.Matchup", "pk":6070403, "fields":{"espn_game_id":240926026, "year":2004, "date":"2004-09-26", "week_number":3, "bye":false, "home_team":7, "away_team":6, "win":true, "home_team_points":34, "away_team_points":0} },
{ "model":"game.Matchup", "pk":8150403, "fields":{"espn_game_id":240926014, "year":2004, "date":"2004-09-26", "week_number":3, "bye":false, "home_team":8, "away_team":15, "win":false, "home_team_points":25, "away_team_points":28} },
{ "model":"game.Matchup", "pk":9120403, "fields":{"espn_game_id":240926016, "year":2004, "date":"2004-09-26", "week_number":3, "bye":false, "home_team":12, "away_team":9, "win":true, "home_team_points":27, "away_team_points":22} },
{ "model":"game.Matchup", "pk":11300403, "fields":{"espn_game_id":240926011, "year":2004, "date":"2004-09-26", "week_number":3, "bye":false, "home_team":30, "away_team":11, "win":true, "home_team_points":45, "away_team_points":31} },
{ "model":"game.Matchup", "pk":14000403, "fields":{"espn_game_id":null, "year":2004, "date":null, "week_number":3, "bye":true, "home_team":14, "away_team":null, "win":null, "home_team_points":null, "away_team_points":null} },
{ "model":"game.Matchup", "pk":16230403, "fields":{"espn_game_id":240926013, "year":2004, "date":"2004-09-26", "week_number":3, "bye":false, "home_team":23, "away_team":16, "win":true, "home_team_points":30, "away_team_points":20} },
{ "model":"game.Matchup", "pk":17000403, "fields":{"espn_game_id":null, "year":2004, "date":null, "week_number":3, "bye":true, "home_team":17, "away_team":null, "win":null, "home_team_points":null, "away_team_points":null} },
{ "model":"game.Matchup", "pk":18280403, "fields":{"espn_game_id":240926015, "year":2004, "date":"2004-09-26", "week_number":3, "bye":false, "home_team":18, "away_team":28, "win":false, "home_team_points":3, "away_team_points":13} },
{ "model":"game.Matchup", "pk":19000403, "fields":{"espn_game_id":null, "year":2004, "date":null, "week_number":3, "bye":true, "home_team":19, "away_team":null, "win":null, "home_team_points":null, "away_team_points":null} },
{ "model":"game.Matchup", "pk":20000403, "fields":{"espn_game_id":null, "year":2004, "date":null, "week_number":3, "bye":true, "home_team":20, "away_team":null, "win":null, "home_team_points":null, "away_team_points":null} },
{ "model":"game.Matchup", "pk":21240403, "fields":{"espn_game_id":240926007, "year":2004, "date":"2004-09-26", "week_number":3, "bye":false, "home_team":21, "away_team":24, "win":true, "home_team_points":23, "away_team_points":13} },
{ "model":"game.Matchup", "pk":22290403, "fields":{"espn_game_id":240926012, "year":2004, "date":"2004-09-26", "week_number":3, "bye":false, "home_team":22, "away_team":29, "win":false, "home_team_points":21, "away_team_points":24} },
{ "model":"game.Matchup", "pk":25260403, "fields":{"espn_game_id":240926004, "year":2004, "date":"2004-09-26", "week_number":3, "bye":false, "home_team":26, "away_team":25, "win":false, "home_team_points":9, "away_team_points":23} },
{ "model":"game.Matchup", "pk":31320403, "fields":{"espn_game_id":240926010, "year":2004, "date":"2004-09-26", "week_number":3, "bye":false, "home_team":32, "away_team":31, "win":false, "home_team_points":12, "away_team_points":15} },
{ "model":"game.Matchup", "pk":1000404, "fields":{"espn_game_id":null, "year":2004, "date":null, "week_number":4, "bye":true, "home_team":1, "away_team":null, "win":null, "home_team_points":null, "away_team_points":null} },
{ "model":"game.Matchup", "pk":2110404, "fields":{"espn_game_id":241003009, "year":2004, "date":"2004-10-03", "week_number":4, "bye":false, "home_team":11, "away_team":2, "win":false, "home_team_points":7, "away_team_points":14} },
{ "model":"game.Matchup", "pk":3090404, "fields":{"espn_game_id":241003003, "year":2004, "date":"2004-10-03", "week_number":4, "bye":false, "home_team":9, "away_team":3, "win":false, "home_team_points":9, "away_team_points":19} },
{ "model":"game.Matchup", "pk":4270404, "fields":{"espn_game_id":241003005, "year":2004, "date":"2004-10-03", "week_number":4, "bye":false, "home_team":27, "away_team":4, "win":true, "home_team_points":17, "away_team_points":13} },
{ "model":"game.Matchup", "pk":5150404, "fields":{"espn_game_id":241003022, "year":2004, "date":"2004-10-03", "week_number":4, "bye":false, "home_team":5, "away_team":15, "win":true, "home_team_points":34, "away_team_points":10} },
{ "model":"game.Matchup", "pk":6080404, "fields":{"espn_game_id":241003025, "year":2004, "date":"2004-10-03", "week_number":4, "bye":false, "home_team":6, "away_team":8, "win":false, "home_team_points":14, "away_team_points":24} },
{ "model":"game.Matchup", "pk":7000404, "fields":{"espn_game_id":null, "year":2004, "date":null, "week_number":4, "bye":true, "home_team":7, "away_team":null, "win":null, "home_team_points":null, "away_team_points":null} },
{ "model":"game.Matchup", "pk":10000404, "fields":{"espn_game_id":null, "year":2004, "date":null, "week_number":4, "bye":true, "home_team":10, "away_team":null, "win":null, "home_team_points":null, "away_team_points":null} },
{ "model":"game.Matchup", "pk":12000404, "fields":{"espn_game_id":null, "year":2004, "date":null, "week_number":4, "bye":true, "home_team":12, "away_team":null, "win":null, "home_team_points":null, "away_team_points":null} },
{ "model":"game.Matchup", "pk":13140404, "fields":{"espn_game_id":241003029, "year":2004, "date":"2004-10-03", "week_number":4, "bye":false, "home_team":14, "away_team":13, "win":false, "home_team_points":10, "away_team_points":27} },
{ "model":"game.Matchup", "pk":16210404, "fields":{"espn_game_id":241003027, "year":2004, "date":"2004-10-03", "week_number":4, "bye":false, "home_team":16, "away_team":21, "win":false, "home_team_points":13, "away_team_points":16} },
{ "model":"game.Matchup", "pk":17190404, "fields":{"espn_game_id":241003002, "year":2004, "date":"2004-10-03", "week_number":4, "bye":false, "home_team":17, "away_team":19, "win":false, "home_team_points":17, "away_team_points":31} },
{ "model":"game.Matchup", "pk":18200404, "fields":{"espn_game_id":241003015, "year":2004, "date":"2004-10-03", "week_number":4, "bye":false, "home_team":18, "away_team":20, "win":false, "home_team_points":9, "away_team_points":17} },
{ "model":"game.Matchup", "pk":22250404, "fields":{"espn_game_id":241004033, "year":2004, "date":"2004-10-04", "week_number":4, "bye":false, "home_team":25, "away_team":22, "win":false, "home_team_points":24, "away_team_points":27} },
{ "model":"game.Matchup", "pk":23290404, "fields":{"espn_game_id":241003034, "year":2004, "date":"2004-10-03", "week_number":4, "bye":false, "home_team":29, "away_team":23, "win":true, "home_team_points":30, "away_team_points":17} },
{ "model":"game.Matchup", "pk":24320404, "fields":{"espn_game_id":241003024, "year":2004, "date":"2004-10-03", "week_number":4, "bye":false, "home_team":24, "away_team":32, "win":true, "home_team_points":38, "away_team_points":17} },
{ "model":"game.Matchup", "pk":26280404, "fields":{"espn_game_id":241003023, "year":2004, "date":"2004-10-03", "week_number":4, "bye":false, "home_team":28, "away_team":26, "win":true, "home_team_points":28, "away_team_points":17} },
{ "model":"game.Matchup", "pk":30310404, "fields":{"espn_game_id":241003030, "year":2004, "date":"2004-10-03", "week_number":4, "bye":false, "home_team":31, "away_team":30, "win":false, "home_team_points":17, "away_team_points":24} },
{ "model":"game.Matchup", "pk":1020405, "fields":{"espn_game_id":241010006, "year":2004, "date":"2004-10-10", "week_number":5, "bye":false, "home_team":1, "away_team":2, "win":false, "home_team_points":10, "away_team_points":26} },
{ "model":"game.Matchup", "pk":3000405, "fields":{"espn_game_id":null, "year":2004, "date":null, "week_number":5, "bye":true, "home_team":3, "away_team":null, "win":null, "home_team_points":null, "away_team_points":null} },
{ "model":"game.Matchup", "pk":4250405, "fields":{"espn_game_id":241010028, "year":2004, "date":"2004-10-10", "week_number":5, "bye":false, "home_team":4, "away_team":25, "win":false, "home_team_points":10, "away_team_points":17} },
{ "model":"game.Matchup", "pk":5060405, "fields":{"espn_game_id":241010025, "year":2004, "date":"2004-10-10", "week_number":5, "bye":false, "home_team":6, "away_team":5, "win":true, "home_team_points":31, "away_team_points":28} },
{ "model":"game.Matchup", "pk":7080405, "fields":{"espn_game_id":241010026, "year":2004, "date":"2004-10-10", "week_number":5, "bye":false, "home_team":7, "away_team":8, "win":false, "home_team_points":27, "away_team_points":33} },
{ "model":"game.Matchup", "pk":9000405, "fields":{"espn_game_id":null, "year":2004, "date":null, "week_number":5, "bye":true, "home_team":9, "away_team":null, "win":null, "home_team_points":null, "away_team_points":null} },
{ "model":"game.Matchup", "pk":10130405, "fields":{"espn_game_id":241010001, "year":2004, "date":"2004-10-10", "week_number":5, "bye":false, "home_team":13, "away_team":10, "win":false, "home_team_points":10, "away_team_points":17} },
{ "model":"game.Matchup", "pk":11320405, "fields":{"espn_game_id":241011009, "year":2004, "date":"2004-10-11", "week_number":5, "bye":false, "home_team":11, "away_team":32, "win":false, "home_team_points":27, "away_team_points":48} },
{ "model":"game.Matchup", "pk":12290405, "fields":{"espn_game_id":241010034, "year":2004, "date":"2004-10-10", "week_number":5, "bye":false, "home_team":29, "away_team":12, "win":false, "home_team_points":28, "away_team_points":34} },
{ "model":"game.Matchup", "pk":14210405, "fields":{"espn_game_id":241010007, "year":2004, "date":"2004-10-10", "week_number":5, "bye":false, "home_team":21, "away_team":14, "win":true, "home_team_points":20, "away_team_points":17} },
{ "model":"game.Matchup", "pk":15160405, "fields":{"espn_game_id":241010018, "year":2004, "date":"2004-10-10", "week_number":5, "bye":false, "home_team":15, "away_team":16, "win":false, "home_team_points":17, "away_team_points":20} },
{ "model":"game.Matchup", "pk":17200405, "fields":{"espn_game_id":241010020, "year":2004, "date":"2004-10-10", "week_number":5, "bye":false, "home_team":20, "away_team":17, "win":true, "home_team_points":16, "away_team_points":14} },
{ "model":"game.Matchup", "pk":18190405, "fields":{"espn_game_id":241010017, "year":2004, "date":"2004-10-10", "week_number":5, "bye":false, "home_team":19, "away_team":18, "win":true, "home_team_points":24, "away_team_points":10} },
{ "model":"game.Matchup", "pk":22000405, "fields":{"espn_game_id":null, "year":2004, "date":null, "week_number":5, "bye":true, "home_team":22, "away_team":null, "win":null, "home_team_points":null, "away_team_points":null} },
{ "model":"game.Matchup", "pk":23300405, "fields":{"espn_game_id":241010011, "year":2004, "date":"2004-10-10", "week_number":5, "bye":false, "home_team":30, "away_team":23, "win":true, "home_team_points":35, "away_team_points":14} },
{ "model":"game.Matchup", "pk":24310405, "fields":{"espn_game_id":241010024, "year":2004, "date":"2004-10-10", "week_number":5, "bye":false, "home_team":24, "away_team":31, "win":true, "home_team_points":34, "away_team_points":21} },
{ "model":"game.Matchup", "pk":26000405, "fields":{"espn_game_id":null, "year":2004, "date":null, "week_number":5, "bye":true, "home_team":26, "away_team":null, "win":null, "home_team_points":null, "away_team_points":null} },
{ "model":"game.Matchup", "pk":27280405, "fields":{"espn_game_id":241010023, "year":2004, "date":"2004-10-10", "week_number":5, "bye":false, "home_team":28, "away_team":27, "win":true, "home_team_points":34, "away_team_points":23} },
{ "model":"game.Matchup", "pk":1280406, "fields":{"espn_game_id":241017006, "year":2004, "date":"2004-10-17", "week_number":6, "bye":false, "home_team":1, "away_team":28, "win":false, "home_team_points":20, "away_team_points":24} },
{ "model":"game.Matchup", "pk":2000406, "fields":{"espn_game_id":null, "year":2004, "date":null, "week_number":6, "bye":true, "home_team":2, "away_team":null, "win":null, "home_team_points":null, "away_team_points":null} },
{ "model":"game.Matchup", "pk":3140406, "fields":{"espn_game_id":241017021, "year":2004, "date":"2004-10-17", "week_number":6, "bye":false, "home_team":3, "away_team":14, "win":true, "home_team_points":30, "away_team_points":8} },
{ "model":"game.Matchup", "pk":4090406, "fields":{"espn_game_id":241017003, "year":2004, "date":"2004-10-17", "week_number":6, "bye":false, "home_team":9, "away_team":4, "win":false, "home_team_points":10, "away_team_points":13} },
{ "model":"game.Matchup", "pk":5000406, "fields":{"espn_game_id":null, "year":2004, "date":null, "week_number":6, "bye":true, "home_team":5, "away_team":null, "win":null, "home_team_points":null, "away_team_points":null} },
{ "model":"game.Matchup", "pk":6200406, "fields":{"espn_game_id":241017020, "year":2004, "date":"2004-10-17", "week_number":6, "bye":false, "home_team":20, "away_team":6, "win":true, "home_team_points":22, "away_team_points":14} },
{ "model":"game.Matchup", "pk":7190406, "fields":{"espn_game_id":241017017, "year":2004, "date":"2004-10-17", "week_number":6, "bye":false, "home_team":19, "away_team":7, "win":true, "home_team_points":30, "away_team_points":20} },
{ "model":"game.Matchup", "pk":8160406, "fields":{"espn_game_id":241018014, "year":2004, "date":"2004-10-18", "week_number":6, "bye":false, "home_team":8, "away_team":16, "win":true, "home_team_points":28, "away_team_points":21} },
{ "model":"game.Matchup", "pk":10110406, "fields":{"espn_game_id":241017008, "year":2004, "date":"2004-10-17", "week_number":6, "bye":false, "home_team":10, "away_team":11, "win":false, "home_team_points":10, "away_team_points":38} },
{ "model":"game.Matchup", "pk":12150406, "fields":{"espn_game_id":241017018, "year":2004, "date":"2004-10-17", "week_number":6, "bye":false, "home_team":15, "away_team":12, "win":false, "home_team_points":31, "away_team_points":38} },
{ "model":"game.Matchup", "pk":13240406, "fields":{"espn_game_id":241017001, "year":2004, "date":"2004-10-17", "week_number":6, "bye":false, "home_team":13, "away_team":24, "win":true, "home_team_points":21, "away_team_points":20} },
{ "model":"game.Matchup", "pk":17180406, "fields":{"espn_game_id":241017002, "year":2004, "date":"2004-10-17", "week_number":6, "bye":false, "home_team":17, "away_team":18, "win":true, "home_team_points":20, "away_team_points":13} },
{ "model":"game.Matchup", "pk":21230406, "fields":{"espn_game_id":241017013, "year":2004, "date":"2004-10-17", "week_number":6, "bye":false, "home_team":23, "away_team":21, "win":false, "home_team_points":3, "away_team_points":31} },
{ "model":"game.Matchup", "pk":22310406, "fields":{"espn_game_id":241017030, "year":2004, "date":"2004-10-17", "week_number":6, "bye":false, "home_team":31, "away_team":22, "win":true, "home_team_points":22, "away_team_points":16} },
{ "model":"game.Matchup", "pk":25000406, "fields":{"espn_game_id":null, "year":2004, "date":null, "week_number":6, "bye":true, "home_team":25, "away_team":null, "win":null, "home_team_points":null, "away_team_points":null} },
{ "model":"game.Matchup", "pk":26270406, "fields":{"espn_game_id":241017005, "year":2004, "date":"2004-10-17", "week_number":6, "bye":false, "home_team":27, "away_team":26, "win":true, "home_team_points":34, "away_team_points":17} },
{ "model":"game.Matchup", "pk":29320406, "fields":{"espn_game_id":241017010, "year":2004, "date":"2004-10-17", "week_number":6, "bye":false, "home_team":32, "away_team":29, "win":false, "home_team_points":10, "away_team_points":20} },
{ "model":"game.Matchup", "pk":30000406, "fields":{"espn_game_id":null, "year":2004, "date":null, "week_number":6, "bye":true, "home_team":30, "away_team":null, "win":null, "home_team_points":null, "away_team_points":null} },
{ "model":"game.Matchup", "pk":1110407, "fields":{"espn_game_id":241024009, "year":2004, "date":"2004-10-24", "week_number":7, "bye":false, "home_team":11, "away_team":1, "win":true, "home_team_points":41, "away_team_points":20} },
{ "model":"game.Matchup", "pk":2100407, "fields":{"espn_game_id":241024019, "year":2004, "date":"2004-10-24", "week_number":7, "bye":false, "home_team":2, "away_team":10, "win":false, "home_team_points":13, "away_team_points":28} },
{ "model":"game.Matchup", "pk":3270407, "fields":{"espn_game_id":241024005, "year":2004, "date":"2004-10-24", "week_number":7, "bye":false, "home_team":27, "away_team":3, "win":false, "home_team_points":31, "away_team_points":34} },
{ "model":"game.Matchup", "pk":4000407, "fields":{"espn_game_id":null, "year":2004, "date":null, "week_number":7, "bye":true, "home_team":4, "away_team":null, "win":null, "home_team_points":null, "away_team_points":null} },
{ "model":"game.Matchup", "pk":5070407, "fields":{"espn_game_id":241024022, "year":2004, "date":"2004-10-24", "week_number":7, "bye":false, "home_team":5, "away_team":7, "win":true, "home_team_points":25, "away_team_points":17} },
{ "model":"game.Matchup", "pk":6000407, "fields":{"espn_game_id":null, "year":2004, "date":null, "week_number":7, "bye":true, "home_team":6, "away_team":null, "win":null, "home_team_points":null, "away_team_points":null} },
{ "model":"game.Matchup", "pk":8180407, "fields":{"espn_game_id":241024015, "year":2004, "date":"2004-10-24", "week_number":7, "bye":false, "home_team":18, "away_team":8, "win":true, "home_team_points":31, "away_team_points":14} },
{ "model":"game.Matchup", "pk":9160407, "fields":{"espn_game_id":241024027, "year":2004, "date":"2004-10-24", "week_number":7, "bye":false, "home_team":16, "away_team":9, "win":true, "home_team_points":19, "away_team_points":7} },
{ "model":"game.Matchup", "pk":12320407, "fields":{"espn_game_id":241024016, "year":2004, "date":"2004-10-24", "week_number":7, "bye":false, "home_team":12, "away_team":32, "win":true, "home_team_points":20, "away_team_points":3} },
{ "model":"game.Matchup", "pk":13220407, "fields":{"espn_game_id":241024012, "year":2004, "date":"2004-10-24", "week_number":7, "bye":false, "home_team":22, "away_team":13, "win":true, "home_team_points":56, "away_team_points":10} },
{ "model":"game.Matchup", "pk":14240407, "fields":{"espn_game_id":241024029, "year":2004, "date":"2004-10-24", "week_number":7, "bye":false, "home_team":14, "away_team":24, "win":false, "home_team_points":6, "away_team_points":17} },
{ "model":"game.Matchup", "pk":15230407, "fields":{"espn_game_id":241024013, "year":2004, "date":"2004-10-24", "week_number":7, "bye":false, "home_team":23, "away_team":15, "win":false, "home_team_points":26, "away_team_points":31} },
{ "model":"game.Matchup", "pk":17250407, "fields":{"espn_game_id":241024033, "year":2004, "date":"2004-10-24", "week_number":7, "bye":false, "home_team":25, "away_team":17, "win":true, "home_team_points":20, "away_team_points":6} },
{ "model":"game.Matchup", "pk":19200407, "fields":{"espn_game_id":241024017, "year":2004, "date":"2004-10-24", "week_number":7, "bye":false, "home_team":19, "away_team":20, "win":true, "home_team_points":13, "away_team_points":7} },
{ "model":"game.Matchup", "pk":21260407, "fields":{"espn_game_id":241025004, "year":2004, "date":"2004-10-25", "week_number":7, "bye":false, "home_team":26, "away_team":21, "win":true, "home_team_points":23, "away_team_points":10} },
{ "model":"game.Matchup", "pk":28000407, "fields":{"espn_game_id":null, "year":2004, "date":null, "week_number":7, "bye":true, "home_team":28, "away_team":null, "win":null, "home_team_points":null, "away_team_points":null} },
{ "model":"game.Matchup", "pk":29000407, "fields":{"espn_game_id":null, "year":2004, "date":null, "week_number":7, "bye":true, "home_team":29, "away_team":null, "win":null, "home_team_points":null, "away_team_points":null} },
{ "model":"game.Matchup", "pk":30310407, "fields":{"espn_game_id":241024011, "year":2004, "date":"2004-10-24", "week_number":7, "bye":false, "home_team":30, "away_team":31, "win":false, "home_team_points":24, "away_team_points":27} },
{ "model":"game.Matchup", "pk":1100408, "fields":{"espn_game_id":241031006, "year":2004, "date":"2004-10-31", "week_number":8, "bye":false, "home_team":1, "away_team":10, "win":true, "home_team_points":31, "away_team_points":21} },
{ "model":"game.Matchup", "pk":2120408, "fields":{"espn_game_id":241031016, "year":2004, "date":"2004-10-31", "week_number":8, "bye":false, "home_team":12, "away_team":2, "win":false, "home_team_points":13, "away_team_points":34} },
{ "model":"game.Matchup", "pk":3250408, "fields":{"espn_game_id":241031021, "year":2004, "date":"2004-10-31", "week_number":8, "bye":false, "home_team":3, "away_team":25, "win":true, "home_team_points":15, "away_team_points":10} },
{ "model":"game.Matchup", "pk":4110408, "fields":{"espn_game_id":241031028, "year":2004, "date":"2004-10-31", "week_number":8, "bye":false, "home_team":4, "away_team":11, "win":false, "home_team_points":14, "away_team_points":28} },
{ "model":"game.Matchup", "pk":5170408, "fields":{"espn_game_id":241031002, "year":2004, "date":"2004-10-31", "week_number":8, "bye":false, "home_team":17, "away_team":5, "win":true, "home_team_points":38, "away_team_points":14} },
{ "model":"game.Matchup", "pk":6090408, "fields":{"espn_game_id":241031003, "year":2004, "date":"2004-10-31", "week_number":8, "bye":false, "home_team":9, "away_team":6, "win":true, "home_team_points":23, "away_team_points":13} },
{ "model":"game.Matchup", "pk":7140408, "fields":{"espn_game_id":241031026, "year":2004, "date":"2004-10-31", "week_number":8, "bye":false, "home_team":7, "away_team":14, "win":true, "home_team_points":23, "away_team_points":17} },
{ "model":"game.Matchup", "pk":8000408, "fields":{"espn_game_id":null, "year":2004, "date":null, "week_number":8, "bye":true, "home_team":8, "away_team":null, "win":null, "home_team_points":null, "away_team_points":null} },
{ "model":"game.Matchup", "pk":13210408, "fields":{"espn_game_id":241031007, "year":2004, "date":"2004-10-31", "week_number":8, "bye":false, "home_team":21, "away_team":13, "win":false, "home_team_points":28, "away_team_points":41} },
{ "model":"game.Matchup", "pk":15000408, "fields":{"espn_game_id":null, "year":2004, "date":null, "week_number":8, "bye":true, "home_team":15, "away_team":null, "win":null, "home_team_points":null, "away_team_points":null} },
{ "model":"game.Matchup", "pk":16000408, "fields":{"espn_game_id":null, "year":2004, "date":null, "week_number":8, "bye":true, "home_team":16, "away_team":null, "win":null, "home_team_points":null, "away_team_points":null} },
{ "model":"game.Matchup", "pk":18200408, "fields":{"espn_game_id":241101020, "year":2004, "date":"2004-11-01", "week_number":8, "bye":false, "home_team":20, "away_team":18, "win":true, "home_team_points":41, "away_team_points":14} },
{ "model":"game.Matchup", "pk":19280408, "fields":{"espn_game_id":241031023, "year":2004, "date":"2004-10-31", "week_number":8, "bye":false, "home_team":28, "away_team":19, "win":true, "home_team_points":34, "away_team_points":20} },
{ "model":"game.Matchup", "pk":22300408, "fields":{"espn_game_id":241031012, "year":2004, "date":"2004-10-31", "week_number":8, "bye":false, "home_team":22, "away_team":30, "win":true, "home_team_points":45, "away_team_points":35} },
{ "model":"game.Matchup", "pk":23240408, "fields":{"espn_game_id":241031024, "year":2004, "date":"2004-10-31", "week_number":8, "bye":false, "home_team":24, "away_team":23, "win":true, "home_team_points":42, "away_team_points":14} },
{ "model":"game.Matchup", "pk":26320408, "fields":{"espn_game_id":241031010, "year":2004, "date":"2004-10-31", "week_number":8, "bye":false, "home_team":32, "away_team":26, "win":true, "home_team_points":27, "away_team_points":20} },
{ "model":"game.Matchup", "pk":27000408, "fields":{"espn_game_id":null, "year":2004, "date":null, "week_number":8, "bye":true, "home_team":27, "away_team":null, "win":null, "home_team_points":null, "away_team_points":null} },
{ "model":"game.Matchup", "pk":29310408, "fields":{"espn_game_id":241031034, "year":2004, "date":"2004-10-31", "week_number":8, "bye":false, "home_team":29, "away_team":31, "win":true, "home_team_points":20, "away_team_points":6} },
{ "model":"game.Matchup", "pk":1260409, "fields":{"espn_game_id":241107004, "year":2004, "date":"2004-11-07", "week_number":9, "bye":false, "home_team":26, "away_team":1, "win":true, "home_team_points":26, "away_team_points":3} },
{ "model":"game.Matchup", "pk":2090409, "fields":{"espn_game_id":241107019, "year":2004, "date":"2004-11-07", "week_number":9, "bye":false, "home_team":2, "away_team":9, "win":false, "home_team_points":21, "away_team_points":28} },
{ "model":"game.Matchup", "pk":3280409, "fields":{"espn_game_id":241107023, "year":2004, "date":"2004-11-07", "week_number":9, "bye":false, "home_team":28, "away_team":3, "win":true, "home_team_points":27, "away_team_points":3} },
{ "model":"game.Matchup", "pk":4100409, "fields":{"espn_game_id":241107008, "year":2004, "date":"2004-11-07", "week_number":9, "bye":false, "home_team":10, "away_team":4, "win":false, "home_team_points":10, "away_team_points":17} },
{ "model":"game.Matchup", "pk":5180409, "fields":{"espn_game_id":241107015, "year":2004, "date":"2004-11-07", "week_number":9, "bye":false, "home_team":18, "away_team":5, "win":false, "home_team_points":23, "away_team_points":24} },
{ "model":"game.Matchup", "pk":6070409, "fields":{"espn_game_id":241107025, "year":2004, "date":"2004-11-07", "week_number":9, "bye":false, "home_team":6, "away_team":7, "win":false, "home_team_points":27, "away_team_points":42} },
{ "model":"game.Matchup", "pk":8190409, "fields":{"espn_game_id":241107014, "year":2004, "date":"2004-11-07", "week_number":9, "bye":false, "home_team":8, "away_team":19, "win":false, "home_team_points":22, "away_team_points":40} },
{ "model":"game.Matchup", "pk":11000409, "fields":{"espn_game_id":null, "year":2004, "date":null, "week_number":9, "bye":true, "home_team":11, "away_team":null, "win":null, "home_team_points":null, "away_team_points":null} },
{ "model":"game.Matchup", "pk":12300409, "fields":{"espn_game_id":241108011, "year":2004, "date":"2004-11-08", "week_number":9, "bye":false, "home_team":30, "away_team":12, "win":true, "home_team_points":31, "away_team_points":28} },
{ "model":"game.Matchup", "pk":13000409, "fields":{"espn_game_id":null, "year":2004, "date":null, "week_number":9, "bye":true, "home_team":13, "away_team":null, "win":null, "home_team_points":null, "away_team_points":null} },
{ "model":"game.Matchup", "pk":14230409, "fields":{"espn_game_id":241107029, "year":2004, "date":"2004-11-07", "week_number":9, "bye":false, "home_team":14, "away_team":23, "win":false, "home_team_points":24, "away_team_points":27} },
{ "model":"game.Matchup", "pk":15240409, "fields":{"espn_game_id":241107024, "year":2004, "date":"2004-11-07", "week_number":9, "bye":false, "home_team":24, "away_team":15, "win":true, "home_team_points":43, "away_team_points":17} },
{ "model":"game.Matchup", "pk":16220409, "fields":{"espn_game_id":241107027, "year":2004, "date":"2004-11-07", "week_number":9, "bye":false, "home_team":16, "away_team":22, "win":true, "home_team_points":34, "away_team_points":31} },
{ "model":"game.Matchup", "pk":17200409, "fields":{"espn_game_id":241107002, "year":2004, "date":"2004-11-07", "week_number":9, "bye":false, "home_team":17, "away_team":20, "win":true, "home_team_points":22, "away_team_points":17} },
{ "model":"game.Matchup", "pk":21290409, "fields":{"espn_game_id":241107007, "year":2004, "date":"2004-11-07", "week_number":9, "bye":false, "home_team":21, "away_team":29, "win":true, "home_team_points":31, "away_team_points":13} },
{ "model":"game.Matchup", "pk":25270409, "fields":{"espn_game_id":241107033, "year":2004, "date":"2004-11-07", "week_number":9, "bye":false, "home_team":25, "away_team":27, "win":true, "home_team_points":27, "away_team_points":13} },
{ "model":"game.Matchup", "pk":31000409, "fields":{"espn_game_id":null, "year":2004, "date":null, "week_number":9, "bye":true, "home_team":31, "away_team":null, "win":null, "home_team_points":null, "away_team_points":null} },
{ "model":"game.Matchup", "pk":32000409, "fields":{"espn_game_id":null, "year":2004, "date":null, "week_number":9, "bye":true, "home_team":32, "away_team":null, "win":null, "home_team_points":null, "away_team_points":null} },
{ "model":"game.Matchup", "pk":1030410, "fields":{"espn_game_id":241115006, "year":2004, "date":"2004-11-15", "week_number":10, "bye":false, "home_team":1, "away_team":3, "win":false, "home_team_points":21, "away_team_points":49} },
{ "model":"game.Matchup", "pk":2050410, "fields":{"espn_game_id":241114022, "year":2004, "date":"2004-11-14", "week_number":10, "bye":false, "home_team":5, "away_team":2, "win":true, "home_team_points":17, "away_team_points":14} },
{ "model":"game.Matchup", "pk":4260410, "fields":{"espn_game_id":241114028, "year":2004, "date":"2004-11-14", "week_number":10, "bye":false, "home_team":4, "away_team":26, "win":false, "home_team_points":10, "away_team_points":17} },
{ "model":"game.Matchup", "pk":6140410, "fields":{"espn_game_id":241114025, "year":2004, "date":"2004-11-14", "week_number":10, "bye":false, "home_team":6, "away_team":14, "win":false, "home_team_points":27, "away_team_points":37} },
{ "model":"game.Matchup", "pk":7080410, "fields":{"espn_game_id":241114014, "year":2004, "date":"2004-11-14", "week_number":10, "bye":false, "home_team":8, "away_team":7, "win":true, "home_team_points":23, "away_team_points":12} },
{ "model":"game.Matchup", "pk":9320410, "fields":{"espn_game_id":241114010, "year":2004, "date":"2004-11-14", "week_number":10, "bye":false, "home_team":32, "away_team":9, "win":false, "home_team_points":17, "away_team_points":19} },
{ "model":"game.Matchup", "pk":10310410, "fields":{"espn_game_id":241114030, "year":2004, "date":"2004-11-14", "week_number":10, "bye":false, "home_team":31, "away_team":10, "win":true, "home_team_points":23, "away_team_points":17} },
{ "model":"game.Matchup", "pk":11120410, "fields":{"espn_game_id":241114009, "year":2004, "date":"2004-11-14", "week_number":10, "bye":false, "home_team":11, "away_team":12, "win":true, "home_team_points":34, "away_team_points":31} },
{ "model":"game.Matchup", "pk":13160410, "fields":{"espn_game_id":241114001, "year":2004, "date":"2004-11-14", "week_number":10, "bye":false, "home_team":13, "away_team":16, "win":true, "home_team_points":24, "away_team_points":14} },
{ "model":"game.Matchup", "pk":15220410, "fields":{"espn_game_id":241114018, "year":2004, "date":"2004-11-14", "week_number":10, "bye":false, "home_team":15, "away_team":22, "win":true, "home_team_points":27, "away_team_points":20} },
{ "model":"game.Matchup", "pk":17190410, "fields":{"espn_game_id":241114017, "year":2004, "date":"2004-11-14", "week_number":10, "bye":false, "home_team":19, "away_team":17, "win":true, "home_team_points":29, "away_team_points":6} },
{ "model":"game.Matchup", "pk":18000410, "fields":{"espn_game_id":null, "year":2004, "date":null, "week_number":10, "bye":true, "home_team":18, "away_team":null, "win":null, "home_team_points":null, "away_team_points":null} },
{ "model":"game.Matchup", "pk":20250410, "fields":{"espn_game_id":241114020, "year":2004, "date":"2004-11-14", "week_number":10, "bye":false, "home_team":20, "away_team":25, "win":false, "home_team_points":17, "away_team_points":20} },
{ "model":"game.Matchup", "pk":21000410, "fields":{"espn_game_id":null, "year":2004, "date":null, "week_number":10, "bye":true, "home_team":21, "away_team":null, "win":null, "home_team_points":null, "away_team_points":null} },
{ "model":"game.Matchup", "pk":23000410, "fields":{"espn_game_id":null, "year":2004, "date":null, "week_number":10, "bye":true, "home_team":23, "away_team":null, "win":null, "home_team_points":null, "away_team_points":null} },
{ "model":"game.Matchup", "pk":24000410, "fields":{"espn_game_id":null, "year":2004, "date":null, "week_number":10, "bye":true, "home_team":24, "away_team":null, "win":null, "home_team_points":null, "away_team_points":null} },
{ "model":"game.Matchup", "pk":27280410, "fields":{"espn_game_id":241114005, "year":2004, "date":"2004-11-14", "week_number":10, "bye":false, "home_team":27, "away_team":28, "win":false, "home_team_points":10, "away_team_points":24} },
{ "model":"game.Matchup", "pk":29300410, "fields":{"espn_game_id":241114011, "year":2004, "date":"2004-11-14", "week_number":10, "bye":false, "home_team":30, "away_team":29, "win":true, "home_team_points":49, "away_team_points":14} },
{ "model":"game.Matchup", "pk":1250411, "fields":{"espn_game_id":241121033, "year":2004, "date":"2004-11-21", "week_number":11, "bye":false, "home_team":25, "away_team":1, "win":true, "home_team_points":30, "away_team_points":10} },
{ "model":"game.Matchup", "pk":2130411, "fields":{"espn_game_id":241121019, "year":2004, "date":"2004-11-21", "week_number":11, "bye":false, "home_team":2, "away_team":13, "win":false, "home_team_points":10, "away_team_points":14} },
{ "model":"game.Matchup", "pk":3040411, "fields":{"espn_game_id":241121021, "year":2004, "date":"2004-11-21", "week_number":11, "bye":false, "home_team":3, "away_team":4, "win":true, "home_team_points":28, "away_team_points":6} },
{ "model":"game.Matchup", "pk":5140411, "fields":{"espn_game_id":241121029, "year":2004, "date":"2004-11-21", "week_number":11, "bye":false, "home_team":14, "away_team":5, "win":true, "home_team_points":35, "away_team_points":10} },
{ "model":"game.Matchup", "pk":6160411, "fields":{"espn_game_id":241121027, "year":2004, "date":"2004-11-21", "week_number":11, "bye":false, "home_team":16, "away_team":6, "win":true, "home_team_points":35, "away_team_points":3} },
{ "model":"game.Matchup", "pk":7180411, "fields":{"espn_game_id":241121026, "year":2004, "date":"2004-11-21", "week_number":11, "bye":false, "home_team":7, "away_team":18, "win":true, "home_team_points":24, "away_team_points":17} },
{ "model":"game.Matchup", "pk":8170411, "fields":{"espn_game_id":241121002, "year":2004, "date":"2004-11-21", "week_number":11, "bye":false, "home_team":17, "away_team":8, "win":true, "home_team_points":37, "away_team_points":17} },
{ "model":"game.Matchup", "pk":9300411, "fields":{"espn_game_id":241121003, "year":2004, "date":"2004-11-21", "week_number":11, "bye":false, "home_team":9, "away_team":30, "win":false, "home_team_points":10, "away_team_points":41} },
{ "model":"game.Matchup", "pk":10120411, "fields":{"espn_game_id":241121016, "year":2004, "date":"2004-11-21", "week_number":11, "bye":false, "home_team":12, "away_team":10, "win":true, "home_team_points":22, "away_team_points":19} },
{ "model":"game.Matchup", "pk":11290411, "fields":{"espn_game_id":241121034, "year":2004, "date":"2004-11-21", "week_number":11, "bye":false, "home_team":29, "away_team":11, "win":false, "home_team_points":13, "away_team_points":16} },
{ "model":"game.Matchup", "pk":15210411, "fields":{"espn_game_id":241121018, "year":2004, "date":"2004-11-21", "week_number":11, "bye":false, "home_team":15, "away_team":21, "win":false, "home_team_points":13, "away_team_points":34} },
{ "model":"game.Matchup", "pk":19220411, "fields":{"espn_game_id":241122012, "year":2004, "date":"2004-11-22", "week_number":11, "bye":false, "home_team":22, "away_team":19, "win":false, "home_team_points":19, "away_team_points":27} },
{ "model":"game.Matchup", "pk":20270411, "fields":{"espn_game_id":241121005, "year":2004, "date":"2004-11-21", "week_number":11, "bye":false, "home_team":27, "away_team":20, "win":false, "home_team_points":7, "away_team_points":10} },
{ "model":"game.Matchup", "pk":23240411, "fields":{"espn_game_id":241121013, "year":2004, "date":"2004-11-21", "week_number":11, "bye":false, "home_team":23, "away_team":24, "win":false, "home_team_points":17, "away_team_points":23} },
{ "model":"game.Matchup", "pk":26280411, "fields":{"espn_game_id":241121004, "year":2004, "date":"2004-11-21", "week_number":11, "bye":false, "home_team":26, "away_team":28, "win":false, "home_team_points":14, "away_team_points":19} },
{ "model":"game.Matchup", "pk":31320411, "fields":{"espn_game_id":241121030, "year":2004, "date":"2004-11-21", "week_number":11, "bye":false, "home_team":31, "away_team":32, "win":false, "home_team_points":15, "away_team_points":18} },
{ "model":"game.Matchup", "pk":1090412, "fields":{"espn_game_id":241125006, "year":2004, "date":"2004-11-25", "week_number":12, "bye":false, "home_team":1, "away_team":9, "win":true, "home_team_points":21, "away_team_points":7} },
{ "model":"game.Matchup", "pk":2030412, "fields":{"espn_game_id":241128019, "year":2004, "date":"2004-11-28", "week_number":12, "bye":false, "home_team":2, "away_team":3, "win":false, "home_team_points":6, "away_team_points":27} },
{ "model":"game.Matchup", "pk":4280412, "fields":{"espn_game_id":241128023, "year":2004, "date":"2004-11-28", "week_number":12, "bye":false, "home_team":28, "away_team":4, "win":true, "home_team_points":16, "away_team_points":7} },
{ "model":"game.Matchup", "pk":5200412, "fields":{"espn_game_id":241128022, "year":2004, "date":"2004-11-28", "week_number":12, "bye":false, "home_team":5, "away_team":20, "win":false, "home_team_points":3, "away_team_points":13} },
{ "model":"game.Matchup", "pk":6180412, "fields":{"espn_game_id":241128025, "year":2004, "date":"2004-11-28", "week_number":12, "bye":false, "home_team":6, "away_team":18, "win":false, "home_team_points":17, "away_team_points":24} },
{ "model":"game.Matchup", "pk":7170412, "fields":{"espn_game_id":241128026, "year":2004, "date":"2004-11-28", "week_number":12, "bye":false, "home_team":7, "away_team":17, "win":false, "home_team_points":9, "away_team_points":38} },
{ "model":"game.Matchup", "pk":8110412, "fields":{"espn_game_id":241129009, "year":2004, "date":"2004-11-29", "week_number":12, "bye":false, "home_team":11, "away_team":8, "win":true, "home_team_points":45, "away_team_points":17} },
{ "model":"game.Matchup", "pk":10300412, "fields":{"espn_game_id":241125008, "year":2004, "date":"2004-11-25", "week_number":12, "bye":false, "home_team":10, "away_team":30, "win":false, "home_team_points":9, "away_team_points":41} },
{ "model":"game.Matchup", "pk":12310412, "fields":{"espn_game_id":241128016, "year":2004, "date":"2004-11-28", "week_number":12, "bye":false, "home_team":12, "away_team":31, "win":true, "home_team_points":27, "away_team_points":16} },
{ "model":"game.Matchup", "pk":13150412, "fields":{"espn_game_id":241128001, "year":2004, "date":"2004-11-28", "week_number":12, "bye":false, "home_team":13, "away_team":15, "win":true, "home_team_points":24, "away_team_points":21} },
{ "model":"game.Matchup", "pk":14160412, "fields":{"espn_game_id":241128029, "year":2004, "date":"2004-11-28", "week_number":12, "bye":false, "home_team":14, "away_team":16, "win":true, "home_team_points":21, "away_team_points":14} },
{ "model":"game.Matchup", "pk":19250412, "fields":{"espn_game_id":241128017, "year":2004, "date":"2004-11-28", "week_number":12, "bye":false, "home_team":19, "away_team":25, "win":true, "home_team_points":24, "away_team_points":3} },
{ "model":"game.Matchup", "pk":21230412, "fields":{"espn_game_id":241128007, "year":2004, "date":"2004-11-28", "week_number":12, "bye":false, "home_team":21, "away_team":23, "win":false, "home_team_points":24, "away_team_points":25} },
{ "model":"game.Matchup", "pk":22240412, "fields":{"espn_game_id":241128012, "year":2004, "date":"2004-11-28", "week_number":12, "bye":false, "home_team":22, "away_team":24, "win":false, "home_team_points":31, "away_team_points":34} },
{ "model":"game.Matchup", "pk":26270412, "fields":{"espn_game_id":241128004, "year":2004, "date":"2004-11-28", "week_number":12, "bye":false, "home_team":26, "away_team":27, "win":true, "home_team_points":58, "away_team_points":48} },
{ "model":"game.Matchup", "pk":29320412, "fields":{"espn_game_id":241128034, "year":2004, "date":"2004-11-28", "week_number":12, "bye":false, "home_team":29, "away_team":32, "win":true, "home_team_points":31, "away_team_points":21} },
{ "model":"game.Matchup", "pk":1070413, "fields":{"espn_game_id":241206026, "year":2004, "date":"2004-12-06", "week_number":13, "bye":false, "home_team":7, "away_team":1, "win":false, "home_team_points":39, "away_team_points":43} },
{ "model":"game.Matchup", "pk":2040413, "fields":{"espn_game_id":241205028, "year":2004, "date":"2004-12-05", "week_number":13, "bye":false, "home_team":4, "away_team":2, "win":true, "home_team_points":31, "away_team_points":7} },
{ "model":"game.Matchup", "pk":3110413, "fields":{"espn_game_id":241205021, "year":2004, "date":"2004-12-05", "week_number":13, "bye":false, "home_team":3, "away_team":11, "win":true, "home_team_points":47, "away_team_points":17} },
{ "model":"game.Matchup", "pk":5100413, "fields":{"espn_game_id":241205008, "year":2004, "date":"2004-12-05", "week_number":13, "bye":false, "home_team":10, "away_team":5, "win":true, "home_team_points":26, "away_team_points":12} },
{ "model":"game.Matchup", "pk":6080413, "fields":{"espn_game_id":241205014, "year":2004, "date":"2004-12-05", "week_number":13, "bye":false, "home_team":8, "away_team":6, "win":true, "home_team_points":16, "away_team_points":6} },
{ "model":"game.Matchup", "pk":9120413, "fields":{"espn_game_id":241205003, "year":2004, "date":"2004-12-05", "week_number":13, "bye":false, "home_team":9, "away_team":12, "win":true, "home_team_points":24, "away_team_points":14} },
{ "model":"game.Matchup", "pk":13160413, "fields":{"espn_game_id":241205027, "year":2004, "date":"2004-12-05", "week_number":13, "bye":false, "home_team":16, "away_team":13, "win":true, "home_team_points":27, "away_team_points":0} },
{ "model":"game.Matchup", "pk":14150413, "fields":{"espn_game_id":241205018, "year":2004, "date":"2004-12-05", "week_number":13, "bye":false, "home_team":15, "away_team":14, "win":false, "home_team_points":21, "away_team_points":32} },
{ "model":"game.Matchup", "pk":17180413, "fields":{"espn_game_id":241205015, "year":2004, "date":"2004-12-05", "week_number":13, "bye":false, "home_team":18, "away_team":17, "win":false, "home_team_points":32, "away_team_points":42} },
{ "model":"game.Matchup", "pk":19270413, "fields":{"espn_game_id":241205005, "year":2004, "date":"2004-12-05", "week_number":13, "bye":false, "home_team":27, "away_team":19, "win":false, "home_team_points":15, "away_team_points":42} },
{ "model":"game.Matchup", "pk":20290413, "fields":{"espn_game_id":241205020, "year":2004, "date":"2004-12-05", "week_number":13, "bye":false, "home_team":20, "away_team":29, "win":true, "home_team_points":29, "away_team_points":7} },
{ "model":"game.Matchup", "pk":21240413, "fields":{"espn_game_id":241205024, "year":2004, "date":"2004-12-05", "week_number":13, "bye":false, "home_team":24, "away_team":21, "win":true, "home_team_points":20, "away_team_points":17} },
{ "model":"game.Matchup", "pk":22230413, "fields":{"espn_game_id":241205013, "year":2004, "date":"2004-12-05", "week_number":13, "bye":false, "home_team":23, "away_team":22, "win":false, "home_team_points":27, "away_team_points":34} },
{ "model":"game.Matchup", "pk":25260413, "fields":{"espn_game_id":241205033, "year":2004, "date":"2004-12-05", "week_number":13, "bye":false, "home_team":25, "away_team":26, "win":false, "home_team_points":26, "away_team_points":27} },
{ "model":"game.Matchup", "pk":28310413, "fields":{"espn_game_id":241205030, "year":2004, "date":"2004-12-05", "week_number":13, "bye":false, "home_team":31, "away_team":28, "win":false, "home_team_points":16, "away_team_points":17} },
{ "model":"game.Matchup", "pk":30320413, "fields":{"espn_game_id":241205011, "year":2004, "date":"2004-12-05", "week_number":13, "bye":false, "home_team":30, "away_team":32, "win":true, "home_team_points":51, "away_team_points":24} },
{ "model":"game.Matchup", "pk":1150414, "fields":{"espn_game_id":241212006, "year":2004, "date":"2004-12-12", "week_number":14, "bye":false, "home_team":1, "away_team":15, "win":false, "home_team_points":13, "away_team_points":27} },
{ "model":"game.Matchup", "pk":2250414, "fields":{"espn_game_id":241212033, "year":2004, "date":"2004-12-12", "week_number":14, "bye":false, "home_team":25, "away_team":2, "win":true, "home_team_points":37, "away_team_points":14} },
{ "model":"game.Matchup", "pk":3040414, "fields":{"espn_game_id":241212028, "year":2004, "date":"2004-12-12", "week_number":14, "bye":false, "home_team":4, "away_team":3, "win":false, "home_team_points":14, "away_team_points":17} },
{ "model":"game.Matchup", "pk":5060414, "fields":{"espn_game_id":241212022, "year":2004, "date":"2004-12-12", "week_number":14, "bye":false, "home_team":5, "away_team":6, "win":false, "home_team_points":28, "away_team_points":31} },
{ "model":"game.Matchup", "pk":7120414, "fields":{"espn_game_id":241212016, "year":2004, "date":"2004-12-12", "week_number":14, "bye":false, "home_team":12, "away_team":7, "win":false, "home_team_points":23, "away_team_points":27} },
{ "model":"game.Matchup", "pk":8140414, "fields":{"espn_game_id":241212029, "year":2004, "date":"2004-12-12", "week_number":14, "bye":false, "home_team":14, "away_team":8, "win":true, "home_team_points":20, "away_team_points":7} },
{ "model":"game.Matchup", "pk":9310414, "fields":{"espn_game_id":241212030, "year":2004, "date":"2004-12-12", "week_number":14, "bye":false, "home_team":31, "away_team":9, "win":true, "home_team_points":22, "away_team_points":3} },
{ "model":"game.Matchup", "pk":10110414, "fields":{"espn_game_id":241212009, "year":2004, "date":"2004-12-12", "week_number":14, "bye":false, "home_team":11, "away_team":10, "win":true, "home_team_points":16, "away_team_points":13} },
{ "model":"game.Matchup", "pk":13230414, "fields":{"espn_game_id":241212001, "year":2004, "date":"2004-12-12", "week_number":14, "bye":false, "home_team":13, "away_team":23, "win":true, "home_team_points":35, "away_team_points":10} },
{ "model":"game.Matchup", "pk":16240414, "fields":{"espn_game_id":241212024, "year":2004, "date":"2004-12-12", "week_number":14, "bye":false, "home_team":24, "away_team":16, "win":true, "home_team_points":31, "away_team_points":24} },
{ "model":"game.Matchup", "pk":17270414, "fields":{"espn_game_id":241212002, "year":2004, "date":"2004-12-12", "week_number":14, "bye":false, "home_team":17, "away_team":27, "win":true, "home_team_points":37, "away_team_points":7} },
{ "model":"game.Matchup", "pk":18210414, "fields":{"espn_game_id":241212007, "year":2004, "date":"2004-12-12", "week_number":14, "bye":false, "home_team":21, "away_team":18, "win":true, "home_team_points":20, "away_team_points":17} },
{ "model":"game.Matchup", "pk":19260414, "fields":{"espn_game_id":241212017, "year":2004, "date":"2004-12-12", "week_number":14, "bye":false, "home_team":19, "away_team":26, "win":true, "home_team_points":35, "away_team_points":28} },
{ "model":"game.Matchup", "pk":20280414, "fields":{"espn_game_id":241212023, "year":2004, "date":"2004-12-12", "week_number":14, "bye":false, "home_team":28, "away_team":20, "win":true, "home_team_points":17, "away_team_points":6} },
{ "model":"game.Matchup", "pk":22320414, "fields":{"espn_game_id":241213010, "year":2004, "date":"2004-12-13", "week_number":14, "bye":false, "home_team":32, "away_team":22, "win":false, "home_team_points":38, "away_team_points":49} },
{ "model":"game.Matchup", "pk":29300414, "fields":{"espn_game_id":241212034, "year":2004, "date":"2004-12-12", "week_number":14, "bye":false, "home_team":29, "away_team":30, "win":false, "home_team_points":14, "away_team_points":23} },
{ "model":"game.Matchup", "pk":1030415, "fields":{"espn_game_id":241219021, "year":2004, "date":"2004-12-19", "week_number":15, "bye":false, "home_team":3, "away_team":1, "win":true, "home_team_points":12, "away_team_points":7} },
{ "model":"game.Matchup", "pk":2280415, "fields":{"espn_game_id":241218019, "year":2004, "date":"2004-12-18", "week_number":15, "bye":false, "home_team":2, "away_team":28, "win":false, "home_team_points":30, "away_team_points":33} },
{ "model":"game.Matchup", "pk":4060415, "fields":{"espn_game_id":241218025, "year":2004, "date":"2004-12-18", "week_number":15, "bye":false, "home_team":6, "away_team":4, "win":false, "home_team_points":16, "away_team_points":26} },
{ "model":"game.Matchup", "pk":5080415, "fields":{"espn_game_id":241219022, "year":2004, "date":"2004-12-19", "week_number":15, "bye":false, "home_team":5, "away_team":8, "win":true, "home_team_points":31, "away_team_points":7} },
{ "model":"game.Matchup", "pk":7200415, "fields":{"espn_game_id":241219020, "year":2004, "date":"2004-12-19", "week_number":15, "bye":false, "home_team":20, "away_team":7, "win":true, "home_team_points":37, "away_team_points":14} },
{ "model":"game.Matchup", "pk":9290415, "fields":{"espn_game_id":241219003, "year":2004, "date":"2004-12-19", "week_number":15, "bye":false, "home_team":9, "away_team":29, "win":false, "home_team_points":5, "away_team_points":24} },
{ "model":"game.Matchup", "pk":10120415, "fields":{"espn_game_id":241219008, "year":2004, "date":"2004-12-19", "week_number":15, "bye":false, "home_team":10, "away_team":12, "win":false, "home_team_points":27, "away_team_points":28} },
{ "model":"game.Matchup", "pk":11310415, "fields":{"espn_game_id":241219009, "year":2004, "date":"2004-12-19", "week_number":15, "bye":false, "home_team":11, "away_team":31, "win":false, "home_team_points":25, "away_team_points":28} },
{ "model":"game.Matchup", "pk":13140415, "fields":{"espn_game_id":241218001, "year":2004, "date":"2004-12-18", "week_number":15, "bye":false, "home_team":13, "away_team":14, "win":true, "home_team_points":34, "away_team_points":31} },
{ "model":"game.Matchup", "pk":15160415, "fields":{"espn_game_id":241219027, "year":2004, "date":"2004-12-19", "week_number":15, "bye":false, "home_team":16, "away_team":15, "win":false, "home_team_points":17, "away_team_points":21} },
{ "model":"game.Matchup", "pk":17260415, "fields":{"espn_game_id":241219004, "year":2004, "date":"2004-12-19", "week_number":15, "bye":false, "home_team":26, "away_team":17, "win":false, "home_team_points":17, "away_team_points":33} },
{ "model":"game.Matchup", "pk":18190415, "fields":{"espn_game_id":241220015, "year":2004, "date":"2004-12-20", "week_number":15, "bye":false, "home_team":18, "away_team":19, "win":true, "home_team_points":29, "away_team_points":28} },
{ "model":"game.Matchup", "pk":21220415, "fields":{"espn_game_id":241219012, "year":2004, "date":"2004-12-19", "week_number":15, "bye":false, "home_team":22, "away_team":21, "win":true, "home_team_points":45, "away_team_points":17} },
{ "model":"game.Matchup", "pk":23320415, "fields":{"espn_game_id":241219013, "year":2004, "date":"2004-12-19", "week_number":15, "bye":false, "home_team":23, "away_team":32, "win":true, "home_team_points":40, "away_team_points":35} },
{ "model":"game.Matchup", "pk":24270415, "fields":{"espn_game_id":241219005, "year":2004, "date":"2004-12-19", "week_number":15, "bye":false, "home_team":27, "away_team":24, "win":false, "home_team_points":0, "away_team_points":21} },
{ "model":"game.Matchup", "pk":25300415, "fields":{"espn_game_id":241219011, "year":2004, "date":"2004-12-19", "week_number":15, "bye":false, "home_team":30, "away_team":25, "win":true, "home_team_points":20, "away_team_points":10} },
{ "model":"game.Matchup", "pk":1040416, "fields":{"espn_game_id":241226006, "year":2004, "date":"2004-12-26", "week_number":16, "bye":false, "home_team":1, "away_team":4, "win":true, "home_team_points":13, "away_team_points":10} },
{ "model":"game.Matchup", "pk":2260416, "fields":{"espn_game_id":241226004, "year":2004, "date":"2004-12-26", "week_number":16, "bye":false, "home_team":26, "away_team":2, "win":true, "home_team_points":23, "away_team_points":22} },
{ "model":"game.Matchup", "pk":3080416, "fields":{"espn_game_id":241227014, "year":2004, "date":"2004-12-27", "week_number":16, "bye":false, "home_team":8, "away_team":3, "win":true, "home_team_points":20, "away_team_points":7} },
{ "model":"game.Matchup", "pk":5070416, "fields":{"espn_game_id":241226026, "year":2004, "date":"2004-12-26", "week_number":16, "bye":false, "home_team":7, "away_team":5, "win":true, "home_team_points":24, "away_team_points":21} },
{ "model":"game.Matchup", "pk":6170416, "fields":{"espn_game_id":241226025, "year":2004, "date":"2004-12-26", "week_number":16, "bye":false, "home_team":6, "away_team":17, "win":false, "home_team_points":7, "away_team_points":41} },
{ "model":"game.Matchup", "pk":9100416, "fields":{"espn_game_id":241226008, "year":2004, "date":"2004-12-26", "week_number":16, "bye":false, "home_team":10, "away_team":9, "win":true, "home_team_points":19, "away_team_points":13} },
{ "model":"game.Matchup", "pk":11120416, "fields":{"espn_game_id":241224016, "year":2004, "date":"2004-12-24", "week_number":16, "bye":false, "home_team":12, "away_team":11, "win":false, "home_team_points":31, "away_team_points":34} },
{ "model":"game.Matchup", "pk":13150416, "fields":{"espn_game_id":241226018, "year":2004, "date":"2004-12-26", "week_number":16, "bye":false, "home_team":15, "away_team":13, "win":true, "home_team_points":26, "away_team_points":13} },
{ "model":"game.Matchup", "pk":14160416, "fields":{"espn_game_id":241226027, "year":2004, "date":"2004-12-26", "week_number":16, "bye":false, "home_team":16, "away_team":14, "win":false, "home_team_points":20, "away_team_points":37} },
{ "model":"game.Matchup", "pk":18270416, "fields":{"espn_game_id":241226015, "year":2004, "date":"2004-12-26", "week_number":16, "bye":false, "home_team":18, "away_team":27, "win":true, "home_team_points":10, "away_team_points":7} },
{ "model":"game.Matchup", "pk":19200416, "fields":{"espn_game_id":241226020, "year":2004, "date":"2004-12-26", "week_number":16, "bye":false, "home_team":20, "away_team":19, "win":false, "home_team_points":7, "away_team_points":23} },
{ "model":"game.Matchup", "pk":21320416, "fields":{"espn_game_id":241225010, "year":2004, "date":"2004-12-25", "week_number":16, "bye":false, "home_team":32, "away_team":21, "win":false, "home_team_points":16, "away_team_points":37} },
{ "model":"game.Matchup", "pk":22230416, "fields":{"espn_game_id":241225012, "year":2004, "date":"2004-12-25", "week_number":16, "bye":false, "home_team":22, "away_team":23, "win":true, "home_team_points":31, "away_team_points":30} },
{ "model":"game.Matchup", "pk":24300416, "fields":{"espn_game_id":241226011, "year":2004, "date":"2004-12-26", "week_number":16, "bye":false, "home_team":30, "away_team":24, "win":true, "home_team_points":34, "away_team_points":31} },
{ "model":"game.Matchup", "pk":25280416, "fields":{"espn_game_id":241226023, "year":2004, "date":"2004-12-26", "week_number":16, "bye":false, "home_team":28, "away_team":25, "win":true, "home_team_points":20, "away_team_points":7} },
{ "model":"game.Matchup", "pk":29310416, "fields":{"espn_game_id":241226030, "year":2004, "date":"2004-12-26", "week_number":16, "bye":false, "home_team":31, "away_team":29, "win":false, "home_team_points":0, "away_team_points":21} },
{ "model":"game.Matchup", "pk":1020417, "fields":{"espn_game_id":250102019, "year":2004, "date":"2004-01-02", "week_number":17, "bye":false, "home_team":2, "away_team":1, "win":true, "home_team_points":28, "away_team_points":24} },
{ "model":"game.Matchup", "pk":3260417, "fields":{"espn_game_id":250102021, "year":2004, "date":"2004-01-02", "week_number":17, "bye":false, "home_team":3, "away_team":26, "win":false, "home_team_points":10, "away_team_points":38} },
{ "model":"game.Matchup", "pk":4120417, "fields":{"espn_game_id":250102028, "year":2004, "date":"2004-01-02", "week_number":17, "bye":false, "home_team":4, "away_team":12, "win":true, "home_team_points":21, "away_team_points":18} },
{ "model":"game.Matchup", "pk":5160417, "fields":{"espn_game_id":250102022, "year":2004, "date":"2004-01-02", "week_number":17, "bye":false, "home_team":5, "away_team":16, "win":true, "home_team_points":12, "away_team_points":7} },
{ "model":"game.Matchup", "pk":6190417, "fields":{"espn_game_id":250102017, "year":2004, "date":"2004-01-02", "week_number":17, "bye":false, "home_team":19, "away_team":6, "win":true, "home_team_points":21, "away_team_points":7} },
{ "model":"game.Matchup", "pk":7130417, "fields":{"espn_game_id":250102026, "year":2004, "date":"2004-01-02", "week_number":17, "bye":false, "home_team":7, "away_team":13, "win":true, "home_team_points":28, "away_team_points":26} },
{ "model":"game.Matchup", "pk":8200417, "fields":{"espn_game_id":250102014, "year":2004, "date":"2004-01-02", "week_number":17, "bye":false, "home_team":8, "away_team":20, "win":true, "home_team_points":32, "away_team_points":29} },
{ "model":"game.Matchup", "pk":9110417, "fields":{"espn_game_id":250102003, "year":2004, "date":"2004-01-02", "week_number":17, "bye":false, "home_team":9, "away_team":11, "win":false, "home_team_points":14, "away_team_points":31} },
{ "model":"game.Matchup", "pk":10320417, "fields":{"espn_game_id":250102010, "year":2004, "date":"2004-01-02", "week_number":17, "bye":false, "home_team":32, "away_team":10, "win":true, "home_team_points":24, "away_team_points":19} },
{ "model":"game.Matchup", "pk":14150417, "fields":{"espn_game_id":250102029, "year":2004, "date":"2004-01-02", "week_number":17, "bye":false, "home_team":14, "away_team":15, "win":false, "home_team_points":18, "away_team_points":21} },
{ "model":"game.Matchup", "pk":17280417, "fields":{"espn_game_id":250102002, "year":2004, "date":"2004-01-02", "week_number":17, "bye":false, "home_team":17, "away_team":28, "win":false, "home_team_points":24, "away_team_points":29} },
{ "model":"game.Matchup", "pk":18250417, "fields":{"espn_game_id":250102033, "year":2004, "date":"2004-01-02", "week_number":17, "bye":false, "home_team":25, "away_team":18, "win":true, "home_team_points":30, "away_team_points":23} },
{ "model":"game.Matchup", "pk":21300417, "fields":{"espn_game_id":250102007, "year":2004, "date":"2004-01-02", "week_number":17, "bye":false, "home_team":21, "away_team":30, "win":true, "home_team_points":33, "away_team_points":14} },
{ "model":"game.Matchup", "pk":22240417, "fields":{"espn_game_id":250102024, "year":2004, "date":"2004-01-02", "week_number":17, "bye":false, "home_team":24, "away_team":22, "win":true, "home_team_points":24, "away_team_points":17} },
{ "model":"game.Matchup", "pk":23310417, "fields":{"espn_game_id":250102013, "year":2004, "date":"2004-01-02", "week_number":17, "bye":false, "home_team":23, "away_team":31, "win":false, "home_team_points":6, "away_team_points":13} },
{ "model":"game.Matchup", "pk":27290417, "fields":{"espn_game_id":250102034, "year":2004, "date":"2004-01-02", "week_number":17, "bye":false, "home_team":29, "away_team":27, "win":false, "home_team_points":14, "away_team_points":22} }
]